odoo8_addon_hr_contract_default_trial_length-8.0.1.0.0.99.dev13-py2.7-nspkg.pth
odoo8_addon_hr_contract_default_trial_length-8.0.1.0.0.99.dev13.dist-info/METADATA
odoo8_addon_hr_contract_default_trial_length-8.0.1.0.0.99.dev13.dist-info/RECORD
odoo8_addon_hr_contract_default_trial_length-8.0.1.0.0.99.dev13.dist-info/WHEEL
odoo8_addon_hr_contract_default_trial_length-8.0.1.0.0.99.dev13.dist-info/namespace_packages.txt
odoo8_addon_hr_contract_default_trial_length-8.0.1.0.0.99.dev13.dist-info/top_level.txt
odoo_addons/hr_contract_default_trial_length/README.rst
odoo_addons/hr_contract_default_trial_length/__init__.py
odoo_addons/hr_contract_default_trial_length/__openerp__.py
odoo_addons/hr_contract_default_trial_length/i18n/ca.po
odoo_addons/hr_contract_default_trial_length/i18n/de.po
odoo_addons/hr_contract_default_trial_length/i18n/es.po
odoo_addons/hr_contract_default_trial_length/i18n/fi.po
odoo_addons/hr_contract_default_trial_length/i18n/fr.po
odoo_addons/hr_contract_default_trial_length/i18n/hr_contract_default_trial_length.pot
odoo_addons/hr_contract_default_trial_length/i18n/it.po
odoo_addons/hr_contract_default_trial_length/i18n/pt_BR.po
odoo_addons/hr_contract_default_trial_length/i18n/ro.po
odoo_addons/hr_contract_default_trial_length/i18n/sl.po
odoo_addons/hr_contract_default_trial_length/i18n/zh_CN.po
odoo_addons/hr_contract_default_trial_length/models/__init__.py
odoo_addons/hr_contract_default_trial_length/models/hr_contract.py
odoo_addons/hr_contract_default_trial_length/models/hr_contract_type.py
odoo_addons/hr_contract_default_trial_length/static/description/icon.png
odoo_addons/hr_contract_default_trial_length/views/hr_contract_type.xml
